{"pageFullName":"page047","menu":[{"item":[{"file":"new_3l3_m8u2a1.mp3","name":"听录音","action":"PlayAudio","version":"PlayAudioV1"},{"file":"new_3l3_m8u2a1.swf","name":"看动画","action":"PlayFlash"},{"file":"m8u2a1-data/data.xml","name":"跟读","action":"FollowRead"},{"file":"m8u2a1-data/data.xml","name":"自读","action":"Read"},{"file":"m8u2a1-data/data.xml","name":"对话","action":"RolePlay"},{"file":"m8u2a1-data/data.xml","name":"背课文","action":"Recite"}],"cid":"3l3_V2_p047_menu_1","y":"134","version":"","x":"23"},{"item":[{"file":"new_3l3_m8u2a2.mp3","name":"听录音","action":"PlayAudio","version":"PlayAudioV1"},{"file":"new_3l3_m8u2a2.swf","name":"看动画","action":"PlayFlash"},{"file":"m8u2a2-data/data.xml","name":"跟读","action":"FollowRead"},{"file":"m8u2a2-data/data.xml","name":"自读","action":"Read"},{"file":"m8u2a2-data/data.xml","name":"对话","action":"RolePlay"},{"file":"m8u2a2-data/data.xml","name":"背课文","action":"Recite"}],"cid":"3l3_V2_p047_menu_2","y":"374","version":"","x":"23"}],"background":[{"file":"3l3_V2_p047.jpg","version":"BackgroundV1"}],"clickRead":[{"text":"P47-A1-T.mp3","height":"22","width":"194","cid":"3l3_V2_p047_translate_2","y":"147","x":"71","version":"ClickReadV1"},{"text":"P47-A2-T.mp3","height":"22","width":"140","cid":"3l3_V2_p047_translate_7","y":"385","x":"71","version":"ClickReadV1"}],"word":[{"text":"fish","height":"17","width":"22","cid":"3l3_V2_p047_word_1","y":"278","x":"126","version":"WordV1"},{"text":"hooray","height":"17","width":"47","cid":"3l3_V2_p047_word_2","y":"439","x":"366","version":"WordV1"}],"translate":[{"height":"33","width":"348","isCR":"1","cid":"3l3_V2_p047_translate_1","y":"88","version":"TranslateV1","x":"144"},{"height":"22","width":"192","cid":"3l3_V2_p047_translate_2","y":"144","version":"TranslateV1","x":"73"},{"height":"34","width":"62","isCR":"1","cid":"3l3_V2_p047_translate_3","y":"260","version":"TranslateV1","x":"100"},{"height":"33","width":"75","isCR":"1","cid":"3l3_V2_p047_translate_4","y":"257","version":"TranslateV1","x":"228"},{"height":"34","width":"94","isCR":"1","cid":"3l3_V2_p047_translate_5","y":"148","version":"TranslateV1","x":"363"},{"height":"17","width":"54","isCR":"1","cid":"3l3_V2_p047_translate_6","y":"264","version":"TranslateV1","x":"402"},{"height":"22","width":"138","cid":"3l3_V2_p047_translate_7","y":"384","version":"TranslateV1","x":"73"},{"height":"34","width":"160","isCR":"1","cid":"3l3_V2_p047_translate_8","y":"421","version":"TranslateV1","x":"154"},{"height":"17","width":"57","isCR":"1","cid":"3l3_V2_p047_translate_9","y":"438","version":"TranslateV1","x":"364"},{"height":"15","width":"87","isCR":"1","cid":"3l3_V2_p047_translate_10","y":"559","version":"TranslateV1","x":"172"},{"height":"15","width":"76","isCR":"1","cid":"3l3_V2_p047_translate_10","y":"576","version":"TranslateV1","x":"149"},{"height":"15","width":"54","isCR":"1","cid":"3l3_V2_p047_translate_11","y":"576","version":"TranslateV1","x":"228"},{"height":"12","width":"137","isCR":"1","cid":"3l3_V2_p047_translate_11","y":"594","version":"TranslateV1","x":"149"},{"height":"14","width":"61","isCR":"1","cid":"3l3_V2_p047_translate_11","y":"608","version":"TranslateV1","x":"186"},{"height":"32","width":"88","isCR":"1","cid":"3l3_V2_p047_translate_12","y":"552","version":"TranslateV1","x":"308"},{"height":"14","width":"42","isCR":"1","cid":"3l3_V2_p047_translate_12","y":"586","version":"TranslateV1","x":"301"},{"height":"14","width":"59","isCR":"1","cid":"3l3_V2_p047_translate_13","y":"586","version":"TranslateV1","x":"346"},{"height":"14","width":"120","isCR":"1","cid":"3l3_V2_p047_translate_13","y":"601","version":"TranslateV1","x":"294"},{"height":"29","width":"74","isCR":"1","cid":"3l3_V2_p047_translate_14","y":"618","version":"TranslateV1","x":"318"}]}