{"pageFullName":"page043","background":[{"file":"3l6_V2_p043.jpg","version":"BackgroundV1"}],"clickRead":[{"text":"P43-A6-T.mp3","height":"17","transcid":"","width":"138","cid":"3l6_V2_p043_tr_1","y":"88","x":"60","version":"ClickReadV1"},{"text":"P43-A7-T.mp3","height":"17","transcid":"","width":"258","cid":"3l6_V2_p043_tr_12","y":"406","x":"61","version":"ClickReadV1"},{"text":"P43-A6-have breakfast.mp3","height":"17","transcid":"","width":"96","cid":"3l6_V2_p043_tr_3","y":"127","x":"163","version":"ClickReadV1"},{"text":"P43-A6-have dinner.mp3","height":"17","transcid":"","width":"77","cid":"3l6_V2_p043_tr_7","y":"157","x":"235","version":"ClickReadV1"},{"text":"P43-A6-go to school.mp3","height":"17","transcid":"","width":"77","cid":"3l6_V2_p043_tr_4","y":"125","x":"290","version":"ClickReadV1"},{"text":"P43-A6-go home.mp3","height":"17","transcid":"","width":"62","cid":"3l6_V2_p043_tr_6","y":"157","x":"136","version":"ClickReadV1"},{"text":"P43-A6-get up.mp3","height":"17","transcid":"","width":"46","cid":"3l6_V2_p043_tr_2","y":"127","x":"79","version":"ClickReadV1"},{"text":"P43-A6-go to bed.mp3","height":"17","transcid":"","width":"66","cid":"3l6_V2_p043_tr_8","y":"156","x":"347","version":"ClickReadV1"},{"text":"P43-A6-have lunch.mp3","height":"17","transcid":"","width":"73","cid":"3l6_V2_p043_tr_5","y":"126","x":"398","version":"ClickReadV1"},{"text":"P43-A6-3.mp3","height":"17","transcid":"","width":"66","cid":"3l6_V2_p043_tr_11","y":"295","x":"65","version":"ClickReadV1"},{"text":"P43-A6-1.mp3","height":"48","transcid":"","width":"94","cid":"3l6_V2_p043_tr_9","y":"213","x":"83","version":"ClickReadV1"},{"text":"P43-A6-2.mp3","height":"50","transcid":"","width":"100","cid":"3l6_V2_p043_tr_10","y":"221","x":"391","version":"ClickReadV1"},{"text":"P43-A7-3.mp3","height":"17","transcid":"","width":"180","cid":"3l6_V2_p043_tr_15","y":"646","x":"57","version":"ClickReadV1"},{"text":"P43-A7-4.mp3","height":"17","transcid":"3l6_V2_p043_tr_16","width":"211","cid":"3l6_V2_p043_tr_16","y":"647","x":"244","version":"ClickReadV1"},{"text":"P43-A7-1.mp3","height":"37","transcid":"","width":"113","cid":"3l6_V2_p043_tr_13","y":"445","x":"67","version":"ClickReadV1"},{"text":"P43-A7-2.mp3","height":"35","transcid":"","width":"91","cid":"3l6_V2_p043_tr_14","y":"457","x":"376","version":"ClickReadV1"}],"translate":[{"height":"17","width":"143","cid":"3l6_V2_p043_tr_1","y":"90","version":"TranslateV1","x":"57"},{"height":"17","width":"43","cid":"3l6_V2_p043_tr_2","y":"126","version":"TranslateV1","x":"79"},{"height":"17","width":"98","cid":"3l6_V2_p043_tr_3","y":"126","version":"TranslateV1","x":"162"},{"height":"17","width":"79","cid":"3l6_V2_p043_tr_4","y":"126","version":"TranslateV1","x":"288"},{"height":"17","width":"71","cid":"3l6_V2_p043_tr_5","y":"126","version":"TranslateV1","x":"397"},{"height":"17","width":"59","cid":"3l6_V2_p043_tr_6","y":"157","version":"TranslateV1","x":"136"},{"height":"17","width":"75","cid":"3l6_V2_p043_tr_7","y":"157","version":"TranslateV1","x":"235"},{"height":"17","width":"62","cid":"3l6_V2_p043_tr_8","y":"157","version":"TranslateV1","x":"348"},{"height":"51","width":"94","cid":"3l6_V2_p043_tr_9","y":"212","version":"TranslateV1","x":"84"},{"height":"50","width":"100","cid":"3l6_V2_p043_tr_10","y":"222","version":"TranslateV1","x":"389"},{"height":"17","width":"61","cid":"3l6_V2_p043_tr_11","y":"294","version":"TranslateV1","x":"67"},{"height":"17","width":"264","cid":"3l6_V2_p043_tr_12","y":"407","version":"TranslateV1","x":"57"},{"height":"34","width":"117","cid":"3l6_V2_p043_tr_13","y":"447","version":"TranslateV1","x":"64"},{"height":"36","width":"91","cid":"3l6_V2_p043_tr_14","y":"459","version":"TranslateV1","x":"376"},{"height":"17","width":"182","cid":"3l6_V2_p043_tr_15","y":"645","version":"TranslateV1","x":"58"},{"height":"17","width":"221","cid":"3l6_V2_p043_tr_16","y":"645","version":"TranslateV1","x":"242"}]}