{"pageFullName":"page039","menu":[{"item":[{"file":"new_audio_3l7_m7u1a2_p38.mp3","name":"听录音","action":"PlayAudio","version":"PlayAudioV1"},{"file":"new_audio_3l7_m7u1a2_p38.swf","name":"看动画","action":"PlayFlash","version":"PlayFlashV1"},{"file":"m7u1a2-data/data.xml","name":"跟读","action":"FollowRead"},{"file":"m7u1a2-data/data.xml","name":"自读","action":"Read"},{"file":"m7u1a2-data/data.xml","name":"对话","action":"RolePlay"},{"file":"m7u1a2-data/data.xml","name":"背课文","action":"Recite"}],"cid":"3l7_V2_p039_me_1","y":"57","showqui":"false","x":"31","version":"MenuV1"}],"background":[{"file":"3l7_V2_p039.jpg","version":"BackgroundV1"}],"clickRead":[{"text":"p39-A2-D1-1.mp3","height":"17","width":"144","cid":"3l7_V2_p039_tr_1","y":"93","x":"130","version":"ClickReadV1"},{"text":"p39-A2-D1-2.mp3","height":"17","width":"135","cid":"3l7_V2_p039_tr_2","y":"93","x":"275","version":"ClickReadV1"},{"text":"p39-A2-D1-2.mp3","height":"17","width":"92","cid":"3l7_V2_p039_tr_2","y":"112","x":"130","version":"ClickReadV1"},{"text":"p39-A2-D2-1.mp3","height":"17","width":"188","cid":"3l7_V2_p039_tr_5","y":"178","x":"130","version":"ClickReadV1"},{"text":"p39-A2-D2-2.mp3","height":"17","width":"86","cid":"3l7_V2_p039_tr_6","y":"178","x":"320","version":"ClickReadV1"},{"text":"p39-A2-D2-2.mp3","height":"17","width":"114","cid":"3l7_V2_p039_tr_6","y":"197","x":"130","version":"ClickReadV1"},{"text":"p39-A2-D3-1.mp3","height":"17","width":"202","cid":"3l7_V2_p039_tr_9","y":"447","x":"130","version":"ClickReadV1"},{"text":"p39-A2-D3-2.mp3","height":"17","width":"107","cid":"3l7_V2_p039_tr_10","y":"447","x":"333","version":"ClickReadV1"},{"text":"p39-A2-G1-1.mp3","height":"17","width":"257","cid":"3l7_V2_p039_tr_3","y":"134","x":"130","version":"ClickReadV1"},{"text":"p39-A2-G1-2.mp3","height":"17","width":"139","cid":"3l7_V2_p039_tr_4","y":"156","x":"130","version":"ClickReadV1"},{"text":"p39-A2-G2.mp3","height":"17","width":"181","cid":"3l7_V2_p039_tr_7","y":"219","x":"130","version":"ClickReadV1"},{"text":"p39-A2-G3.mp3","height":"17","width":"160","cid":"3l7_V2_p039_tr_8","y":"426","x":"130","version":"ClickReadV1"},{"text":"p39-A2-G4.mp3","height":"17","width":"160","cid":"3l7_V2_p039_tr_11","y":"468","x":"130","version":"ClickReadV1"}],"word":[{"text":"its","height":"17","width":"14","cid":"3l7_V2_p039_wo_1","y":"94","x":"394","version":"WordV1"},{"text":"body","height":"17","width":"30","cid":"3l7_V2_p039_wo_2","y":"114","x":"132","version":"WordV1"},{"text":"come out of","height":"17","width":"71","cid":"3l7_V2_p039_wo_3","y":"135","x":"259","version":"WordV1"},{"text":"flute","height":"17","width":"25","cid":"3l7_V2_p039_wo_4","y":"197","x":"133","version":"WordV1"},{"text":"get","height":"17","width":"26","cid":"3l7_V2_p039_wo_5","y":"220","x":"215","version":"WordV1"},{"text":"frightened","height":"17","width":"62","cid":"3l7_V2_p039_wo_6","y":"220","x":"245","version":"WordV1"}],"translate":[{"height":"17","width":"146","cid":"3l7_V2_p039_tr_1","y":"94","version":"TranslateV1","x":"128"},{"height":"17","width":"138","cid":"3l7_V2_p039_tr_2","y":"94","version":"TranslateV1","x":"275"},{"height":"17","width":"100","cid":"3l7_V2_p039_tr_2","y":"114","version":"TranslateV1","x":"128"},{"height":"17","width":"262","cid":"3l7_V2_p039_tr_3","y":"135","version":"TranslateV1","x":"128"},{"height":"17","width":"145","cid":"3l7_V2_p039_tr_4","y":"157","version":"TranslateV1","x":"128"},{"height":"17","width":"190","cid":"3l7_V2_p039_tr_5","y":"178","version":"TranslateV1","x":"128"},{"height":"17","width":"90","cid":"3l7_V2_p039_tr_6","y":"178","version":"TranslateV1","x":"319"},{"height":"17","width":"118","cid":"3l7_V2_p039_tr_6","y":"198","version":"TranslateV1","x":"128"},{"height":"17","width":"182","cid":"3l7_V2_p039_tr_7","y":"219","version":"TranslateV1","x":"128"},{"height":"17","width":"159","cid":"3l7_V2_p039_tr_8","y":"426","version":"TranslateV1","x":"128"},{"height":"17","width":"205","cid":"3l7_V2_p039_tr_9","y":"448","version":"TranslateV1","x":"128"},{"height":"17","width":"106","cid":"3l7_V2_p039_tr_10","y":"448","version":"TranslateV1","x":"334"},{"height":"17","width":"160","cid":"3l7_V2_p039_tr_11","y":"470","version":"TranslateV1","x":"128"}]}